maker_circulars/__init__.py
maker_circulars/__main__.py
maker_circulars/constants.py
maker_circulars/databases.py
maker_circulars/prompts.py
maker_circulars/resources.py
maker_circulars/server.py
maker_circulars/tool_schema.py
maker_circulars/tools.py
maker_circulars/utils.py
utils/__init__.py
utils/llm.py
syia_mcp_maker_circulars_2025_x7k9-0.1.31.dist-info/METADATA
syia_mcp_maker_circulars_2025_x7k9-0.1.31.dist-info/WHEEL
syia_mcp_maker_circulars_2025_x7k9-0.1.31.dist-info/top_level.txt
syia_mcp_maker_circulars_2025_x7k9-0.1.31.dist-info/RECORD
