Metadata-Version: 2.4
Name: syia-mcp-maker-circulars-2025-x7k9
Version: 0.1.31
Summary: MCP Maker Circulars Module
Project-URL: Repository, https://github.com/syia-ai/mcp-data-science
Project-URL: Homepage, https://github.com/syia-ai/mcp-data-science
Requires-Python: >=3.12
Requires-Dist: cohere>=5.15.0
Requires-Dist: colorama>=0.4.6
Requires-Dist: loguru>=0.7.3
Requires-Dist: mcp>=1.8.0
Requires-Dist: motor>=3.7.0
Requires-Dist: openai>=1.78.1
Requires-Dist: playwright>=1.52.0
Requires-Dist: pydantic>=2.11.4
Requires-Dist: pymongo>=4.12.1
Requires-Dist: python-dateutil>=2.8.2
Requires-Dist: python-dotenv>=1.0.0
Requires-Dist: requests>=2.32.3
Requires-Dist: typesense>=1.0.3
Requires-Dist: httpx>=0.25.2
